odoo/addons/l10n_th_promptpay/README.rst
odoo/addons/l10n_th_promptpay/__init__.py
odoo/addons/l10n_th_promptpay/__manifest__.py
odoo/addons/l10n_th_promptpay/data/payment_icon_data.xml
odoo/addons/l10n_th_promptpay/i18n/l10n_th_promptpay.pot
odoo/addons/l10n_th_promptpay/i18n/th_TH.po
odoo/addons/l10n_th_promptpay/models/__init__.py
odoo/addons/l10n_th_promptpay/models/payment_provider.py
odoo/addons/l10n_th_promptpay/readme/CONTRIBUTORS.rst
odoo/addons/l10n_th_promptpay/readme/CREDITS.rst
odoo/addons/l10n_th_promptpay/readme/DESCRIPTION.rst
odoo/addons/l10n_th_promptpay/readme/HISTORY.rst
odoo/addons/l10n_th_promptpay/readme/USAGE.rst
odoo/addons/l10n_th_promptpay/static/description/icon.png
odoo/addons/l10n_th_promptpay/static/description/index.html
odoo/addons/l10n_th_promptpay/static/description/promptpay_QR_code.png
odoo/addons/l10n_th_promptpay/static/description/promptpay_configuration.png
odoo/addons/l10n_th_promptpay/static/description/website_confirm_order.png
odoo/addons/l10n_th_promptpay/static/img/baac.png
odoo/addons/l10n_th_promptpay/static/img/bay.png
odoo/addons/l10n_th_promptpay/static/img/bbl.png
odoo/addons/l10n_th_promptpay/static/img/bnp.png
odoo/addons/l10n_th_promptpay/static/img/boa.png
odoo/addons/l10n_th_promptpay/static/img/cacib.png
odoo/addons/l10n_th_promptpay/static/img/cimb.png
odoo/addons/l10n_th_promptpay/static/img/citi.png
odoo/addons/l10n_th_promptpay/static/img/db.png
odoo/addons/l10n_th_promptpay/static/img/ghb.png
odoo/addons/l10n_th_promptpay/static/img/gsb.png
odoo/addons/l10n_th_promptpay/static/img/hsbc.png
odoo/addons/l10n_th_promptpay/static/img/ibank.png
odoo/addons/l10n_th_promptpay/static/img/icbc.png
odoo/addons/l10n_th_promptpay/static/img/jpm.png
odoo/addons/l10n_th_promptpay/static/img/kbank.png
odoo/addons/l10n_th_promptpay/static/img/kk.png
odoo/addons/l10n_th_promptpay/static/img/ktb.png
odoo/addons/l10n_th_promptpay/static/img/lhb.png
odoo/addons/l10n_th_promptpay/static/img/mb.png
odoo_addon_l10n_th_promptpay-16.0.1.0.0.2.dist-info/METADATA
odoo_addon_l10n_th_promptpay-16.0.1.0.0.2.dist-info/WHEEL
odoo_addon_l10n_th_promptpay-16.0.1.0.0.2.dist-info/top_level.txt
odoo_addon_l10n_th_promptpay-16.0.1.0.0.2.dist-info/RECORD
