Metadata-Version: 2.1
Name: odoo-addon-l10n_th_promptpay
Version: 16.0.1.0.0.2
Summary: Use PromptPay QR code with transfer acquirer.
Home-page: https://github.com/OCA/l10n-thailand
Author: Poonlap V.,Odoo Community Association (OCA)
Author-email: support@odoo-community.org
License: AGPL-3
Classifier: Programming Language :: Python
Classifier: Framework :: Odoo
Classifier: Framework :: Odoo :: 16.0
Classifier: License :: OSI Approved :: GNU Affero General Public License v3
Requires-Python: >=3.10
Requires-Dist: odoo <16.1dev,>=16.0a
Requires-Dist: promptpay
